acous/__init__.py
acous/acoustics/__init__.py
acous/acoustics/spl.py
acous/fft/__init__.py
acous/fft/basic.py
acous/plot/__init__.py
acous/plot/plot_setup.py
acous/signal/__init__.py
acous/signal/spectral.py
acous/signal/windows/__init__.py
acous/signal/windows/windows.py
acous-0.0.1.dist-info/LICENSE
acous-0.0.1.dist-info/METADATA
acous-0.0.1.dist-info/WHEEL
acous-0.0.1.dist-info/top_level.txt
acous-0.0.1.dist-info/RECORD
